{
	"name": "DIM_TITLE",
	"properties": {
		"activities": [
			{
				"name": "Data flow1",
				"type": "ExecuteDataFlow",
				"dependsOn": [],
				"policy": {
					"timeout": "0.12:00:00",
					"retry": 0,
					"retryIntervalInSeconds": 30,
					"secureOutput": false,
					"secureInput": false
				},
				"userProperties": [],
				"typeProperties": {
					"dataflow": {
						"referenceName": "df_dim_Title",
						"type": "DataFlowReference",
						"datasetParameters": {
							"sourcetable": {
								"tablename": "TITLES"
							},
							"sink1": {
								"tablename": "DIM_TITLE"
							}
						}
					},
					"compute": {
						"coreCount": 8,
						"computeType": "General"
					},
					"traceLevel": "Fine"
				}
			}
		],
		"annotations": []
	}
}